aionostr_dvm/__init__.py
aionostr_dvm/aionostr_dvm.py
aionostr_dvm-0.0.5.dist-info/licenses/LICENSE
aionostr_dvm-0.0.5.dist-info/METADATA
aionostr_dvm-0.0.5.dist-info/WHEEL
aionostr_dvm-0.0.5.dist-info/top_level.txt
aionostr_dvm-0.0.5.dist-info/RECORD
