Metadata-Version: 2.4
Name: aionostr-dvm
Version: 0.0.5
Summary: Simple Framework for NIP-89/90 Data Vending Machines using electrum-aionostr asyncio nostr library
Author-email: f321x <f@f321x.com>
License: MIT
Project-URL: Homepage, https://github.com/f321x/aionostr-dvm
Requires-Python: >=3.11
License-File: LICENSE
Requires-Dist: electrum-aionostr[crypto]
Requires-Dist: certifi
Dynamic: license-file
